{
"meta":{"test_sets":[],"test_metrics":[],"learn_metrics":[{"best_value":"Min","name":"RMSE"}],"launch_mode":"Train","parameters":"","iteration_count":300,"learn_sets":["learn"],"name":"experiment"},
"iterations":[
{"learn":[689.652509],"iteration":0,"passed_time":0.001588722374,"remaining_time":0.4750279898},
{"learn":[659.416496],"iteration":1,"passed_time":0.002881431768,"remaining_time":0.4293333335},
{"learn":[624.1698949],"iteration":2,"passed_time":0.003975259712,"remaining_time":0.3935507115},
{"learn":[593.6912843],"iteration":3,"passed_time":0.005152629486,"remaining_time":0.3812945819},
{"learn":[566.9646254],"iteration":4,"passed_time":0.006329488331,"remaining_time":0.3734398115},
{"learn":[542.4606939],"iteration":5,"passed_time":0.007402578586,"remaining_time":0.3627263507},
{"learn":[518.9665903],"iteration":6,"passed_time":0.008458778143,"remaining_time":0.3540602851},
{"learn":[498.9405938],"iteration":7,"passed_time":0.009558326482,"remaining_time":0.3488789166},
{"learn":[480.719261],"iteration":8,"passed_time":0.01065345679,"remaining_time":0.3444617696},
{"learn":[464.8284319],"iteration":9,"passed_time":0.01147766472,"remaining_time":0.332852277},
{"learn":[449.3423447],"iteration":10,"passed_time":0.01273863644,"remaining_time":0.3346787209},
{"learn":[434.4616329],"iteration":11,"passed_time":0.01387821753,"remaining_time":0.3330772208},
{"learn":[422.6427977],"iteration":12,"passed_time":0.01505158002,"remaining_time":0.3322925744},
{"learn":[409.364759],"iteration":13,"passed_time":0.01628423027,"remaining_time":0.3326635612},
{"learn":[397.8599015],"iteration":14,"passed_time":0.01758737863,"remaining_time":0.334160194},
{"learn":[387.6245739],"iteration":15,"passed_time":0.01888345359,"remaining_time":0.3351813012},
{"learn":[377.6571218],"iteration":16,"passed_time":0.02008707107,"remaining_time":0.3343906536},
{"learn":[368.188299],"iteration":17,"passed_time":0.02130479418,"remaining_time":0.3337751088},
{"learn":[361.4657005],"iteration":18,"passed_time":0.02253059197,"remaining_time":0.333215597},
{"learn":[353.9220975],"iteration":19,"passed_time":0.0238213979,"remaining_time":0.3334995706},
{"learn":[347.3679398],"iteration":20,"passed_time":0.02513365282,"remaining_time":0.3339185303},
{"learn":[341.4121618],"iteration":21,"passed_time":0.02645446328,"remaining_time":0.3342882179},
{"learn":[334.7758722],"iteration":22,"passed_time":0.02771106706,"remaining_time":0.3337376337},
{"learn":[328.9278644],"iteration":23,"passed_time":0.0289486663,"remaining_time":0.3329096624},
{"learn":[323.268358],"iteration":24,"passed_time":0.03022095914,"remaining_time":0.3324305505},
{"learn":[318.7451336],"iteration":25,"passed_time":0.03170867238,"remaining_time":0.3341606243},
{"learn":[314.5597615],"iteration":26,"passed_time":0.0330288517,"remaining_time":0.3339583894},
{"learn":[308.7680117],"iteration":27,"passed_time":0.03428561577,"remaining_time":0.3330602675},
{"learn":[305.2605197],"iteration":28,"passed_time":0.03557167307,"remaining_time":0.3324111518},
{"learn":[302.2581602],"iteration":29,"passed_time":0.03687799721,"remaining_time":0.3319019749},
{"learn":[298.0526286],"iteration":30,"passed_time":0.03816671936,"remaining_time":0.3311886293},
{"learn":[294.6863168],"iteration":31,"passed_time":0.03946288503,"remaining_time":0.3305016622},
{"learn":[291.6022449],"iteration":32,"passed_time":0.0407449857,"remaining_time":0.3296639752},
{"learn":[288.6595957],"iteration":33,"passed_time":0.0420710958,"remaining_time":0.3291444554},
{"learn":[286.5539],"iteration":34,"passed_time":0.04333690631,"remaining_time":0.3281222906},
{"learn":[284.1260768],"iteration":35,"passed_time":0.04469031602,"remaining_time":0.3277289842},
{"learn":[281.393372],"iteration":36,"passed_time":0.04625484888,"remaining_time":0.3287844663},
{"learn":[278.8360297],"iteration":37,"passed_time":0.04777476175,"remaining_time":0.32939441},
{"learn":[276.8650059],"iteration":38,"passed_time":0.04908919062,"remaining_time":0.328519968},
{"learn":[275.1847202],"iteration":39,"passed_time":0.05037676067,"remaining_time":0.3274489444},
{"learn":[273.1044405],"iteration":40,"passed_time":0.05174396546,"remaining_time":0.3268704159},
{"learn":[271.0724841],"iteration":41,"passed_time":0.05309493073,"remaining_time":0.3261545745},
{"learn":[268.5299859],"iteration":42,"passed_time":0.05448906445,"remaining_time":0.3256671992},
{"learn":[266.0960953],"iteration":43,"passed_time":0.05580181026,"remaining_time":0.3246650779},
{"learn":[264.4146923],"iteration":44,"passed_time":0.05719862886,"remaining_time":0.3241255636},
{"learn":[262.9514057],"iteration":45,"passed_time":0.05857155404,"remaining_time":0.3234168419},
{"learn":[261.7420979],"iteration":46,"passed_time":0.05992081566,"remaining_time":0.3225524758},
{"learn":[259.8475407],"iteration":47,"passed_time":0.06155843245,"remaining_time":0.3231817704},
{"learn":[258.0985172],"iteration":48,"passed_time":0.0630328315,"remaining_time":0.3228824634},
{"learn":[256.4364869],"iteration":49,"passed_time":0.06443848616,"remaining_time":0.3221924308},
{"learn":[254.1932412],"iteration":50,"passed_time":0.06578788859,"remaining_time":0.3211996914},
{"learn":[252.0588023],"iteration":51,"passed_time":0.06746623496,"remaining_time":0.3217620437},
{"learn":[249.8059524],"iteration":52,"passed_time":0.06881940424,"remaining_time":0.3207243933},
{"learn":[248.579757],"iteration":53,"passed_time":0.07016644237,"remaining_time":0.3196471263},
{"learn":[246.9809917],"iteration":54,"passed_time":0.07154573913,"remaining_time":0.318703747},
{"learn":[245.9697145],"iteration":55,"passed_time":0.07301553982,"remaining_time":0.3181391378},
{"learn":[244.5047682],"iteration":56,"passed_time":0.07449287475,"remaining_time":0.3175748871},
{"learn":[243.1794939],"iteration":57,"passed_time":0.076001742,"remaining_time":0.3171107166},
{"learn":[241.8066288],"iteration":58,"passed_time":0.07765372378,"remaining_time":0.3171957192},
{"learn":[240.2018045],"iteration":59,"passed_time":0.07903864076,"remaining_time":0.316154563},
{"learn":[239.4248692],"iteration":60,"passed_time":0.08035727727,"remaining_time":0.314842447},
{"learn":[238.3449579],"iteration":61,"passed_time":0.08173000209,"remaining_time":0.31373775},
{"learn":[237.1429124],"iteration":62,"passed_time":0.08307489632,"remaining_time":0.3125198481},
{"learn":[236.4364319],"iteration":63,"passed_time":0.08437511937,"remaining_time":0.3111332527},
{"learn":[235.2671886],"iteration":64,"passed_time":0.08576159919,"remaining_time":0.3100611663},
{"learn":[233.986884],"iteration":65,"passed_time":0.08745561793,"remaining_time":0.3100699181},
{"learn":[232.2590331],"iteration":66,"passed_time":0.08887986694,"remaining_time":0.3090896865},
{"learn":[231.1621505],"iteration":67,"passed_time":0.09024397554,"remaining_time":0.3078912107},
{"learn":[229.2357619],"iteration":68,"passed_time":0.09170771577,"remaining_time":0.3070214832},
{"learn":[228.1729087],"iteration":69,"passed_time":0.09309363457,"remaining_time":0.305879085},
{"learn":[227.1741642],"iteration":70,"passed_time":0.0944217984,"remaining_time":0.3045435469},
{"learn":[226.3555765],"iteration":71,"passed_time":0.0957334422,"remaining_time":0.3031559003},
{"learn":[224.2568874],"iteration":72,"passed_time":0.09704342299,"remaining_time":0.3017651646},
{"learn":[223.596293],"iteration":73,"passed_time":0.09841690919,"remaining_time":0.3005705605},
{"learn":[222.4299354],"iteration":74,"passed_time":0.0998390438,"remaining_time":0.2995171314},
{"learn":[221.2199014],"iteration":75,"passed_time":0.1012996884,"remaining_time":0.2985675027},
{"learn":[220.3328254],"iteration":76,"passed_time":0.1026633968,"remaining_time":0.2973238636},
{"learn":[218.9552446],"iteration":77,"passed_time":0.1040686007,"remaining_time":0.2961952481},
{"learn":[217.6777572],"iteration":78,"passed_time":0.1054700883,"remaining_time":0.2950492344},
{"learn":[216.3490205],"iteration":79,"passed_time":0.1069439965,"remaining_time":0.2940959903},
{"learn":[214.4950049],"iteration":80,"passed_time":0.1082894417,"remaining_time":0.2927825646},
{"learn":[213.4059068],"iteration":81,"passed_time":0.109607427,"remaining_time":0.2913953548},
{"learn":[212.4380063],"iteration":82,"passed_time":0.110930181,"remaining_time":0.2900222806},
{"learn":[210.9621591],"iteration":83,"passed_time":0.1123855661,"remaining_time":0.2889914557},
{"learn":[209.7403513],"iteration":84,"passed_time":0.1138382763,"remaining_time":0.2879438753},
{"learn":[208.3654091],"iteration":85,"passed_time":0.1152288641,"remaining_time":0.2867322898},
{"learn":[206.952691],"iteration":86,"passed_time":0.1166985746,"remaining_time":0.2857103034},
{"learn":[206.0476476],"iteration":87,"passed_time":0.1180532066,"remaining_time":0.2844009067},
{"learn":[205.2650624],"iteration":88,"passed_time":0.1194068467,"remaining_time":0.2830881422},
{"learn":[204.304142],"iteration":89,"passed_time":0.1208910346,"remaining_time":0.2820790808},
{"learn":[203.4656017],"iteration":90,"passed_time":0.1230418486,"remaining_time":0.2825906192},
{"learn":[202.424177],"iteration":91,"passed_time":0.1243870434,"remaining_time":0.2812228806},
{"learn":[201.2846274],"iteration":92,"passed_time":0.1257408538,"remaining_time":0.2798748036},
{"learn":[200.1491037],"iteration":93,"passed_time":0.1270534694,"remaining_time":0.2784363265},
{"learn":[199.3182866],"iteration":94,"passed_time":0.1283564374,"remaining_time":0.2769796807},
{"learn":[198.4653521],"iteration":95,"passed_time":0.1298423323,"remaining_time":0.2759149562},
{"learn":[197.2116183],"iteration":96,"passed_time":0.1311606583,"remaining_time":0.2744908622},
{"learn":[196.353468],"iteration":97,"passed_time":0.1325800379,"remaining_time":0.273277221},
{"learn":[195.2628996],"iteration":98,"passed_time":0.1341314074,"remaining_time":0.2723274029},
{"learn":[194.4310939],"iteration":99,"passed_time":0.1357291311,"remaining_time":0.2714582622},
{"learn":[193.7612836],"iteration":100,"passed_time":0.1378851601,"remaining_time":0.2716747214},
{"learn":[193.0246545],"iteration":101,"passed_time":0.1392711685,"remaining_time":0.2703499153},
{"learn":[192.7938224],"iteration":102,"passed_time":0.1406463082,"remaining_time":0.2690031332},
{"learn":[192.6337068],"iteration":103,"passed_time":0.1420211163,"remaining_time":0.2676551807},
{"learn":[191.5025279],"iteration":104,"passed_time":0.1433988402,"remaining_time":0.2663121318},
{"learn":[191.0596059],"iteration":105,"passed_time":0.1447190596,"remaining_time":0.2648631845},
{"learn":[189.9939173],"iteration":106,"passed_time":0.1460809547,"remaining_time":0.2634918155},
{"learn":[189.5881703],"iteration":107,"passed_time":0.1474349555,"remaining_time":0.2621065876},
{"learn":[188.609848],"iteration":108,"passed_time":0.1487721157,"remaining_time":0.2606924229},
{"learn":[187.2178966],"iteration":109,"passed_time":0.1501830199,"remaining_time":0.2594070344},
{"learn":[187.0463801],"iteration":110,"passed_time":0.1517923046,"remaining_time":0.2584571674},
{"learn":[186.7133675],"iteration":111,"passed_time":0.1531978992,"remaining_time":0.2571536165},
{"learn":[186.5837785],"iteration":112,"passed_time":0.1545069383,"remaining_time":0.2556884731},
{"learn":[185.6848335],"iteration":113,"passed_time":0.1558786913,"remaining_time":0.2543283911},
{"learn":[185.5611818],"iteration":114,"passed_time":0.1572481507,"remaining_time":0.2529644164},
{"learn":[184.8550039],"iteration":115,"passed_time":0.1586078619,"remaining_time":0.2515848844},
{"learn":[184.4018972],"iteration":116,"passed_time":0.1599610813,"remaining_time":0.2501955374},
{"learn":[183.6499507],"iteration":117,"passed_time":0.1613267733,"remaining_time":0.2488260402},
{"learn":[183.4962583],"iteration":118,"passed_time":0.1626362031,"remaining_time":0.2473710316},
{"learn":[183.3558126],"iteration":119,"passed_time":0.1639563123,"remaining_time":0.2459344684},
{"learn":[182.3470635],"iteration":120,"passed_time":0.1655832786,"remaining_time":0.2449537758},
{"learn":[180.9027301],"iteration":121,"passed_time":0.1670181664,"remaining_time":0.2436822428},
{"learn":[180.2946187],"iteration":122,"passed_time":0.1683736799,"remaining_time":0.2422938321},
{"learn":[179.7536833],"iteration":123,"passed_time":0.1696787318,"remaining_time":0.240834329},
{"learn":[179.2307879],"iteration":124,"passed_time":0.1709967271,"remaining_time":0.239395418},
{"learn":[178.4275641],"iteration":125,"passed_time":0.1724123098,"remaining_time":0.2380931898},
{"learn":[177.3029689],"iteration":126,"passed_time":0.1738108816,"remaining_time":0.2367660041},
{"learn":[177.2016676],"iteration":127,"passed_time":0.1751633897,"remaining_time":0.2353758049},
{"learn":[176.449314],"iteration":128,"passed_time":0.1765310353,"remaining_time":0.2340062561},
{"learn":[176.1596048],"iteration":129,"passed_time":0.1778790953,"remaining_time":0.2326111246},
{"learn":[175.350466],"iteration":130,"passed_time":0.1792733292,"remaining_time":0.2312762796},
{"learn":[174.7663689],"iteration":131,"passed_time":0.1807179847,"remaining_time":0.2300047078},
{"learn":[174.6912734],"iteration":132,"passed_time":0.1822504354,"remaining_time":0.2288407722},
{"learn":[174.1940178],"iteration":133,"passed_time":0.183685223,"remaining_time":0.2275503509},
{"learn":[173.8293891],"iteration":134,"passed_time":0.1850277724,"remaining_time":0.2261450552},
{"learn":[173.3824615],"iteration":135,"passed_time":0.1868017058,"remaining_time":0.2252608806},
{"learn":[172.8654717],"iteration":136,"passed_time":0.1881727977,"remaining_time":0.2238844235},
{"learn":[172.4059558],"iteration":137,"passed_time":0.1895115708,"remaining_time":0.2224701048},
{"learn":[171.5701603],"iteration":138,"passed_time":0.1908042601,"remaining_time":0.2210034956},
{"learn":[171.217063],"iteration":139,"passed_time":0.1921465396,"remaining_time":0.2195960453},
{"learn":[170.5972701],"iteration":140,"passed_time":0.193463453,"remaining_time":0.2181609151},
{"learn":[170.5137894],"iteration":141,"passed_time":0.1947781529,"remaining_time":0.2167249871},
{"learn":[169.6272355],"iteration":142,"passed_time":0.1963750446,"remaining_time":0.2156005734},
{"learn":[169.1931923],"iteration":143,"passed_time":0.1977780645,"remaining_time":0.2142595698},
{"learn":[168.5647851],"iteration":144,"passed_time":0.1991314642,"remaining_time":0.2128646686},
{"learn":[168.257497],"iteration":145,"passed_time":0.2006590504,"remaining_time":0.2116540669},
{"learn":[167.9932957],"iteration":146,"passed_time":0.2021706838,"remaining_time":0.2104225484},
{"learn":[167.2573643],"iteration":147,"passed_time":0.2035274396,"remaining_time":0.2090281812},
{"learn":[166.6363299],"iteration":148,"passed_time":0.2048358075,"remaining_time":0.2075852814},
{"learn":[165.6652402],"iteration":149,"passed_time":0.2061704931,"remaining_time":0.2061704931},
{"learn":[164.7706148],"iteration":150,"passed_time":0.207509667,"remaining_time":0.2047611946},
{"learn":[164.4773123],"iteration":151,"passed_time":0.2088117935,"remaining_time":0.2033167463},
{"learn":[164.0204811],"iteration":152,"passed_time":0.2103500386,"remaining_time":0.2021010174},
{"learn":[163.6837886],"iteration":153,"passed_time":0.211907975,"remaining_time":0.2008997685},
{"learn":[162.9213455],"iteration":154,"passed_time":0.2132601424,"remaining_time":0.1995014236},
{"learn":[161.8882795],"iteration":155,"passed_time":0.2146933872,"remaining_time":0.1981785113},
{"learn":[161.3873608],"iteration":156,"passed_time":0.2160217013,"remaining_time":0.1967586197},
{"learn":[161.1797779],"iteration":157,"passed_time":0.2172879026,"remaining_time":0.1952840643},
{"learn":[160.7020916],"iteration":158,"passed_time":0.2186306028,"remaining_time":0.1938799685},
{"learn":[160.2500231],"iteration":159,"passed_time":0.220011222,"remaining_time":0.1925098192},
{"learn":[159.4890143],"iteration":160,"passed_time":0.2213348175,"remaining_time":0.1910903083},
{"learn":[158.7740753],"iteration":161,"passed_time":0.222646852,"remaining_time":0.1896621332},
{"learn":[158.4735455],"iteration":162,"passed_time":0.2239018429,"remaining_time":0.1881874385},
{"learn":[157.5970796],"iteration":163,"passed_time":0.2253000034,"remaining_time":0.1868341491},
{"learn":[157.3349914],"iteration":164,"passed_time":0.2268564921,"remaining_time":0.1856098572},
{"learn":[156.7118182],"iteration":165,"passed_time":0.2282398062,"remaining_time":0.1842417713},
{"learn":[156.3682265],"iteration":166,"passed_time":0.2295574209,"remaining_time":0.1828211795},
{"learn":[155.6013254],"iteration":167,"passed_time":0.2308918361,"remaining_time":0.181415014},
{"learn":[154.7190434],"iteration":168,"passed_time":0.232190897,"remaining_time":0.1799822929},
{"learn":[154.0151853],"iteration":169,"passed_time":0.233650109,"remaining_time":0.1786736128},
{"learn":[153.090462],"iteration":170,"passed_time":0.2349467055,"remaining_time":0.1772404971},
{"learn":[152.4669747],"iteration":171,"passed_time":0.236262076,"remaining_time":0.1758229403},
{"learn":[152.2844488],"iteration":172,"passed_time":0.2375589931,"remaining_time":0.174393018},
{"learn":[151.6627954],"iteration":173,"passed_time":0.238875676,"remaining_time":0.1729789378},
{"learn":[151.0026843],"iteration":174,"passed_time":0.2402683571,"remaining_time":0.1716202551},
{"learn":[150.5681839],"iteration":175,"passed_time":0.241776158,"remaining_time":0.1703422931},
{"learn":[150.095026],"iteration":176,"passed_time":0.2432763745,"remaining_time":0.1690564636},
{"learn":[149.5513849],"iteration":177,"passed_time":0.2448358988,"remaining_time":0.1678088745},
{"learn":[149.0774425],"iteration":178,"passed_time":0.2467538607,"remaining_time":0.1668000958},
{"learn":[148.7080989],"iteration":179,"passed_time":0.2481629716,"remaining_time":0.1654419811},
{"learn":[148.5515125],"iteration":180,"passed_time":0.24949916,"remaining_time":0.1640353594},
{"learn":[148.4153932],"iteration":181,"passed_time":0.2508518084,"remaining_time":0.1626401834},
{"learn":[148.1374089],"iteration":182,"passed_time":0.2521778784,"remaining_time":0.1612284796},
{"learn":[148.0385037],"iteration":183,"passed_time":0.2535608017,"remaining_time":0.1598535489},
{"learn":[147.515863],"iteration":184,"passed_time":0.2548151714,"remaining_time":0.1583986201},
{"learn":[147.3131135],"iteration":185,"passed_time":0.2563787832,"remaining_time":0.1571353832},
{"learn":[147.1590044],"iteration":186,"passed_time":0.258278946,"remaining_time":0.1560723043},
{"learn":[146.7418946],"iteration":187,"passed_time":0.2595904696,"remaining_time":0.1546496415},
{"learn":[146.0622495],"iteration":188,"passed_time":0.260878771,"remaining_time":0.1532145163},
{"learn":[145.5618775],"iteration":189,"passed_time":0.262196055,"remaining_time":0.1517977161},
{"learn":[144.7644308],"iteration":190,"passed_time":0.2635538327,"remaining_time":0.1504050668},
{"learn":[144.2736706],"iteration":191,"passed_time":0.2648713472,"remaining_time":0.1489901328},
{"learn":[143.8065957],"iteration":192,"passed_time":0.2661889418,"remaining_time":0.1475762527},
{"learn":[143.2683917],"iteration":193,"passed_time":0.2675158533,"remaining_time":0.146168456},
{"learn":[142.6089125],"iteration":194,"passed_time":0.2687965509,"remaining_time":0.1447366043},
{"learn":[142.0799638],"iteration":195,"passed_time":0.2701398628,"remaining_time":0.143339519},
{"learn":[141.4807539],"iteration":196,"passed_time":0.2719588982,"remaining_time":0.1421917082},
{"learn":[141.3931455],"iteration":197,"passed_time":0.2734492279,"remaining_time":0.1408677841},
{"learn":[140.873716],"iteration":198,"passed_time":0.2750811643,"remaining_time":0.1396140583},
{"learn":[140.7732338],"iteration":199,"passed_time":0.2764647322,"remaining_time":0.1382323661},
{"learn":[140.1164355],"iteration":200,"passed_time":0.2778111793,"remaining_time":0.1368323719},
{"learn":[139.5059036],"iteration":201,"passed_time":0.279183864,"remaining_time":0.135445637},
{"learn":[139.0741101],"iteration":202,"passed_time":0.280510475,"remaining_time":0.134037025},
{"learn":[138.6269509],"iteration":203,"passed_time":0.2818660186,"remaining_time":0.1326428323},
{"learn":[138.5427214],"iteration":204,"passed_time":0.2831577162,"remaining_time":0.1312194294},
{"learn":[138.5163859],"iteration":205,"passed_time":0.284498002,"remaining_time":0.1298194767},
{"learn":[138.179897],"iteration":206,"passed_time":0.2861353739,"remaining_time":0.1285535738},
{"learn":[137.9131016],"iteration":207,"passed_time":0.2880372315,"remaining_time":0.1274010832},
{"learn":[137.6599623],"iteration":208,"passed_time":0.289401511,"remaining_time":0.1260073565},
{"learn":[137.1614287],"iteration":209,"passed_time":0.2907535682,"remaining_time":0.1246086721},
{"learn":[136.9426476],"iteration":210,"passed_time":0.2921333459,"remaining_time":0.1232221222},
{"learn":[136.5728924],"iteration":211,"passed_time":0.2934516017,"remaining_time":0.1218100988},
{"learn":[136.2944884],"iteration":212,"passed_time":0.2947937509,"remaining_time":0.1204087152},
{"learn":[136.1296176],"iteration":213,"passed_time":0.2962575312,"remaining_time":0.1190567649},
{"learn":[135.7144414],"iteration":214,"passed_time":0.2975736632,"remaining_time":0.1176454017},
{"learn":[135.4220148],"iteration":215,"passed_time":0.2989011859,"remaining_time":0.1162393501},
{"learn":[135.0683984],"iteration":216,"passed_time":0.3002856108,"remaining_time":0.1148557866},
{"learn":[134.64036],"iteration":217,"passed_time":0.3020143326,"remaining_time":0.1136017215},
{"learn":[134.2004651],"iteration":218,"passed_time":0.3034118024,"remaining_time":0.1122208036},
{"learn":[133.9046409],"iteration":219,"passed_time":0.3047878934,"remaining_time":0.1108319612},
{"learn":[133.7464165],"iteration":220,"passed_time":0.3061358331,"remaining_time":0.1094331711},
{"learn":[133.2319151],"iteration":221,"passed_time":0.307478864,"remaining_time":0.1080331144},
{"learn":[132.7609825],"iteration":222,"passed_time":0.3088898183,"remaining_time":0.1066570225},
{"learn":[132.4191755],"iteration":223,"passed_time":0.3102395213,"remaining_time":0.1052598376},
{"learn":[131.7525997],"iteration":224,"passed_time":0.3115661323,"remaining_time":0.1038553774},
{"learn":[131.3446993],"iteration":225,"passed_time":0.3129011686,"remaining_time":0.1024543649},
{"learn":[131.3196949],"iteration":226,"passed_time":0.3144772931,"remaining_time":0.1011314643},
{"learn":[130.8712777],"iteration":227,"passed_time":0.3161134166,"remaining_time":0.09982528945},
{"learn":[130.4497678],"iteration":228,"passed_time":0.3176752495,"remaining_time":0.09849319964},
{"learn":[130.0394884],"iteration":229,"passed_time":0.3189732385,"remaining_time":0.09707881172},
{"learn":[129.9220604],"iteration":230,"passed_time":0.3202332184,"remaining_time":0.09565407823},
{"learn":[129.3780735],"iteration":231,"passed_time":0.3214965845,"remaining_time":0.09423175752},
{"learn":[128.6953161],"iteration":232,"passed_time":0.3228210015,"remaining_time":0.09282835666},
{"learn":[128.2218951],"iteration":233,"passed_time":0.3241442063,"remaining_time":0.09142528897},
{"learn":[127.8553301],"iteration":234,"passed_time":0.3254318565,"remaining_time":0.0900130667},
{"learn":[127.4129904],"iteration":235,"passed_time":0.3267408656,"remaining_time":0.08860769235},
{"learn":[126.9154205],"iteration":236,"passed_time":0.3281324647,"remaining_time":0.08722508555},
{"learn":[126.6366934],"iteration":237,"passed_time":0.3294730811,"remaining_time":0.08582912198},
{"learn":[126.3756658],"iteration":238,"passed_time":0.3309126574,"remaining_time":0.0844588791},
{"learn":[125.9423484],"iteration":239,"passed_time":0.3325415929,"remaining_time":0.08313539823},
{"learn":[125.603802],"iteration":240,"passed_time":0.3339400044,"remaining_time":0.08175294714},
{"learn":[125.1568883],"iteration":241,"passed_time":0.3352727466,"remaining_time":0.08035462521},
{"learn":[124.8175996],"iteration":242,"passed_time":0.336651332,"remaining_time":0.0789675964},
{"learn":[124.2553106],"iteration":243,"passed_time":0.3379804977,"remaining_time":0.07756929455},
{"learn":[123.9022277],"iteration":244,"passed_time":0.3392894766,"remaining_time":0.07616702537},
{"learn":[123.8205859],"iteration":245,"passed_time":0.3406217719,"remaining_time":0.07477063285},
{"learn":[123.28766],"iteration":246,"passed_time":0.3420307726,"remaining_time":0.07339121841},
{"learn":[122.9718073],"iteration":247,"passed_time":0.3433650776,"remaining_time":0.07199590337},
{"learn":[122.6411395],"iteration":248,"passed_time":0.3446827423,"remaining_time":0.07059767012},
{"learn":[122.2714872],"iteration":249,"passed_time":0.3463240609,"remaining_time":0.06926481217},
{"learn":[121.8117126],"iteration":250,"passed_time":0.3479897576,"remaining_time":0.06793425546},
{"learn":[121.4180318],"iteration":251,"passed_time":0.3493843421,"remaining_time":0.0665493985},
{"learn":[121.0891817],"iteration":252,"passed_time":0.3507315005,"remaining_time":0.06515565424},
{"learn":[120.8097147],"iteration":253,"passed_time":0.3521044056,"remaining_time":0.0637669396},
{"learn":[120.3965794],"iteration":254,"passed_time":0.3534540986,"remaining_time":0.06237425269},
{"learn":[120.3162841],"iteration":255,"passed_time":0.3549393523,"remaining_time":0.06100520118},
{"learn":[120.2120024],"iteration":256,"passed_time":0.356611247,"remaining_time":0.05966647323},
{"learn":[120.1891431],"iteration":257,"passed_time":0.358124918,"remaining_time":0.05829940525},
{"learn":[119.9683141],"iteration":258,"passed_time":0.3597379395,"remaining_time":0.05694693251},
{"learn":[119.7652405],"iteration":259,"passed_time":0.3618542869,"remaining_time":0.05566989029},
{"learn":[119.3391086],"iteration":260,"passed_time":0.3637962691,"remaining_time":0.05436036205},
{"learn":[118.7749089],"iteration":261,"passed_time":0.3657215754,"remaining_time":0.05304358727},
{"learn":[118.3705511],"iteration":262,"passed_time":0.3672623757,"remaining_time":0.05166809087},
{"learn":[118.2015396],"iteration":263,"passed_time":0.3686907316,"remaining_time":0.05027600885},
{"learn":[117.9153286],"iteration":264,"passed_time":0.3706576903,"remaining_time":0.04895478928},
{"learn":[117.5467703],"iteration":265,"passed_time":0.3722593712,"remaining_time":0.04758202489},
{"learn":[117.0005928],"iteration":266,"passed_time":0.3736838701,"remaining_time":0.04618564687},
{"learn":[116.6517645],"iteration":267,"passed_time":0.3750836541,"remaining_time":0.04478610795},
{"learn":[116.5061289],"iteration":268,"passed_time":0.37658351,"remaining_time":0.04339809966},
{"learn":[116.4847246],"iteration":269,"passed_time":0.3779942439,"remaining_time":0.04199936043},
{"learn":[116.4723566],"iteration":270,"passed_time":0.3793646745,"remaining_time":0.04059621978},
{"learn":[116.2757951],"iteration":271,"passed_time":0.3808501142,"remaining_time":0.03920515881},
{"learn":[116.0655522],"iteration":272,"passed_time":0.3821961505,"remaining_time":0.03779961928},
{"learn":[115.8667089],"iteration":273,"passed_time":0.3836653606,"remaining_time":0.0364062021},
{"learn":[115.5785921],"iteration":274,"passed_time":0.3851817616,"remaining_time":0.03501652378},
{"learn":[115.1317724],"iteration":275,"passed_time":0.3866539572,"remaining_time":0.03362208323},
{"learn":[114.9880973],"iteration":276,"passed_time":0.3880562056,"remaining_time":0.03222127339},
{"learn":[114.9049711],"iteration":277,"passed_time":0.3894086035,"remaining_time":0.03081650819},
{"learn":[114.544421],"iteration":278,"passed_time":0.3910925139,"remaining_time":0.02943707094},
{"learn":[114.3479774],"iteration":279,"passed_time":0.3927513637,"remaining_time":0.02805366884},
{"learn":[113.9639292],"iteration":280,"passed_time":0.3941296887,"remaining_time":0.02664933838},
{"learn":[113.8104098],"iteration":281,"passed_time":0.3955124918,"remaining_time":0.0252454782},
{"learn":[113.5333608],"iteration":282,"passed_time":0.3969073669,"remaining_time":0.02384249201},
{"learn":[113.3926691],"iteration":283,"passed_time":0.3984073831,"remaining_time":0.02244548637},
{"learn":[113.2089516],"iteration":284,"passed_time":0.3998760823,"remaining_time":0.0210461096},
{"learn":[113.1188458],"iteration":285,"passed_time":0.4012606887,"remaining_time":0.01964213162},
{"learn":[112.8368546],"iteration":286,"passed_time":0.4026262505,"remaining_time":0.01823742598},
{"learn":[112.7824842],"iteration":287,"passed_time":0.4039889471,"remaining_time":0.0168328728},
{"learn":[112.2281182],"iteration":288,"passed_time":0.4054941427,"remaining_time":0.01543403311},
{"learn":[111.8936777],"iteration":289,"passed_time":0.4069888241,"remaining_time":0.01403409738},
{"learn":[111.7984314],"iteration":290,"passed_time":0.4083291,"remaining_time":0.01262873505},
{"learn":[111.4687294],"iteration":291,"passed_time":0.4097229732,"remaining_time":0.01122528694},
{"learn":[111.3085155],"iteration":292,"passed_time":0.4112634579,"remaining_time":0.009825406845},
{"learn":[111.2976512],"iteration":293,"passed_time":0.4126068495,"remaining_time":0.008420547948},
{"learn":[110.8991948],"iteration":294,"passed_time":0.4139836216,"remaining_time":0.007016671553},
{"learn":[110.4958887],"iteration":295,"passed_time":0.4153576588,"remaining_time":0.005612941335},
{"learn":[110.0932784],"iteration":296,"passed_time":0.4167335694,"remaining_time":0.004209429994},
{"learn":[109.5833556],"iteration":297,"passed_time":0.4180803371,"remaining_time":0.002805908302},
{"learn":[109.363677],"iteration":298,"passed_time":0.41950157,"remaining_time":0.001403015284},
{"learn":[109.3537962],"iteration":299,"passed_time":0.4210776044,"remaining_time":0}
]}